[
      {
         "Artist": "Eugenie Tung",
         "Title": "16 Windows",
         "Station": "New Lots Avenue",
         "Line": "BMT Canarsie Line",
         "Year": 2007
      },
      {
         "Artist": "Robert Kushner",
         "Title": "4 Seasons Seasoned",
         "Station": "77th Street",
         "Line": "IRT East Side Line",
         "Year": 2004
      },
      {
         "Artist": "Lynn Saville",
         "Title": "42nd Street Nocturne",
         "Station": "42nd Street/Bryant Park",
         "Line": "IND 6th Avenue Line",
         "Year": 2006
      },
      {
         "Artist": "Gerald Marks",
         "Title": "7 waves 4 twenty eight",
         "Station": "28th Street",
         "Line": "IRT East Side Line",
         "Year": 1996
      },
      {
         "Artist": "Elizabeth Grajales",
         "Title": "A Bird's Life",
         "Station": "34th Street/Penn Station",
         "Line": "IRT West Side Line",
         "Year": 1997
      },
      {
         "Artist": "Carol Sun",
         "Title": "A Bronx Reflection",
         "Station": "167th Street",
         "Line": "IRT Woodlawn Line",
         "Year": 2006
      },
      {
         "Artist": "Susanna Starr",
         "Title": "A Continuous Thread",
         "Station": "79th Street",
         "Line": "BMT West End Line",
         "Year": 2012
      },
      {
         "Artist": "William Low",
         "Title": "A Day in Parkchester",
         "Station": "East 177th Street/Parkchester",
         "Line": "IRT Pelham Line",
         "Year": 2010
      },
      {
         "Artist": "Martin/Munoz",
         "Title": "A Gathering",
         "Station": "Canal Street-Holland Tunnel",
         "Line": "IND 8th Avenue Line",
         "Year": 2001
      },
      {
         "Artist": "Yayoi Kusama",
         "Title": "A Message of Love, Directly from My Heart unto the Universe",
         "Station": "Grand Central Madison",
         "Line": "LIRR Main Line",
         "Year": 2022
      },
      {
         "Artist": "Ellsworth Ausby",
         "Title": "A Space Odyssey",
         "Station": "Marcy Avenue",
         "Line": "BMT Nassau Street-Jamaica Line",
         "Year": 2005
      },
      {
         "Artist": "Daniel Del Valle",
         "Title": "A Trip Up The Bronx River",
         "Station": "174th Street",
         "Line": "IRT White Plains Road Line",
         "Year": 2004
      },
      {
         "Artist": "Zach DeSart",
         "Title": "A Way To Go",
         "Station": "Bowling Green",
         "Line": "IRT East Side Line",
         "Year": 2009
      },
      {
         "Artist": "Derek Lerner",
         "Title": "AVEX1-6",
         "Station": "Avenue X",
         "Line": "BMT Culver Line",
         "Year": 2017
      },
      {
         "Artist": "Nancy Baker",
         "Title": "Ailanthus and Chandelier",
         "Station": "Sutter Avenue/Rutland Road, Saratoga Avenue",
         "Line": "IRT Brooklyn Line",
         "Year": 2017
      },
      {
         "Artist": "Liliana Porter",
         "Title": "Alice: The Way Out",
         "Station": "50th Street",
         "Line": "IRT West Side Line",
         "Year": 1994
      },
      {
         "Artist": "Béatrice Coron",
         "Title": "All Around Town",
         "Station": "Subway Car Interior Art",
         "Line": "",
         "Year": 2009
      },
      {
         "Artist": "James Gulliver Hancock",
         "Title": "All the Stuff on the Subway",
         "Station": "Subway Car Interior Art",
         "Line": "",
         "Year": 2014
      },
      {
         "Artist": "Michele Brody",
         "Title": "Allerton Mandalas",
         "Station": "Allerton Avenue",
         "Line": "IRT White Plains Road Line",
         "Year": 2006
      },
      {
         "Artist": "Susan Leopold",
         "Title": "Alleyways, Tribeca",
         "Station": "Franklin Street",
         "Line": "IRT West Side Line",
         "Year": 2005
      },
      {
         "Artist": "Owen Smith",
         "Title": "An Underground Movement: Designers, Builders, Riders",
         "Station": "36th Street",
         "Line": "BMT 4th Avenue Line",
         "Year": 1998
      },
      {
         "Artist": "SOL'SAX",
         "Title": "Ancestral Letters in SOL'SCRYPT",
         "Station": "Halsey Street",
         "Line": "BMT Nassau Street-Jamaica Line",
         "Year": 2007
      },
      {
         "Artist": "Naomi Campbell",
         "Title": "Animal Tracks",
         "Station": "West Farms Sq./East Tremont Ave./177th St.",
         "Line": "IRT White Plains Road Line",
         "Year": 2005
      },
      {
         "Artist": "Jackie Ferrara",
         "Title": "Arches, Towers, Pyramids",
         "Station": "Grand Central",
         "Line": "IRT Times Square-Grand Central Shuttle",
         "Year": 1997
      },
      {
         "Artist": "Derrick Adams",
         "Title": "Around the Way",
         "Station": "Nostrand Avenue",
         "Line": "LIRR Flatbush Avenue Line",
         "Year": 2019
      },
      {
         "Artist": "Nancy Spero",
         "Title": "Artemis, Acrobats, Divas and Dancers",
         "Station": "66th Street/Lincoln Center",
         "Line": "IRT West Side Line",
         "Year": 2004
      },
      {
         "Artist": "Ellen Driscoll",
         "Title": "As Above, So Below",
         "Station": "Grand Central Terminal",
         "Line": "Metro-North Grand Central/Park Avenue Tunnel",
         "Year": 1998
      },
      {
         "Artist": "Nancy Holt",
         "Title": "Astral Grating",
         "Station": "Fulton Street (Broadway/Nassau), Fulton Street",
         "Line": "IND 8th Avenue Line",
         "Year": 1987
      },
      {
         "Artist": "Sheila Levrant de Bretteville",
         "Title": "At the Start... At Long Last",
         "Station": "207th Street",
         "Line": "IND 8th Avenue Line",
         "Year": 1999
      },
      {
         "Artist": "Candida Alvarez",
         "Title": "B is for Birds in the Bronx",
         "Station": "Bronx Park East",
         "Line": "IRT White Plains Road Line",
         "Year": 2006
      },
      {
         "Artist": "Tomie Arai",
         "Title": "Back to the Garden",
         "Station": "Pelham Parkway",
         "Line": "IRT White Plains Road Line",
         "Year": 2006
      },
      {
         "Artist": "Duke Riley",
         "Title": "Be Good or Be Gone",
         "Station": "Beach 98th Street/Playland",
         "Line": "IND Rockaway Line",
         "Year": 2011
      },
      {
         "Artist": "Rico Gatson",
         "Title": "Beacons",
         "Station": "167th Street",
         "Line": "IND Concourse Line",
         "Year": 2019
      },
      {
         "Artist": "Briarwood Students",
         "Title": "Beautifying Briarwood",
         "Station": "Briarwood/Van Wyck Boulevard",
         "Line": "IND Queens Boulevard Line",
         "Year": null
      },
      {
         "Artist": "Christopher Russell",
         "Title": "Bees for Sunset Park",
         "Station": "9th Avenue",
         "Line": "BMT West End Line",
         "Year": 2012
      },
      {
         "Artist": "Francesco Simeti",
         "Title": "Bensonhurst Gardens",
         "Station": "18th Avenue",
         "Line": "BMT West End Line",
         "Year": 2012
      },
      {
         "Artist": "Rita MacDonald",
         "Title": "Bird Laid Bare",
         "Station": "Avenue J",
         "Line": "BMT Brighton Line",
         "Year": 2011
      },
      {
         "Artist": "Wopo Holup",
         "Title": "Birds in Flight-Moon View",
         "Station": "Dyckman Street",
         "Line": "IRT West Side Line",
         "Year": 1991
      },
      {
         "Artist": "Dave Calver",
         "Title": "Bling (a.k.a. Hand)",
         "Station": "Subway Car Interior Art",
         "Line": "",
         "Year": 2005
      },
      {
         "Artist": "Antenna Design New York",
         "Title": "Bloemendaal",
         "Station": "96th Street",
         "Line": "IRT West Side Line",
         "Year": 2010
      },
      {
         "Artist": "Elizabeth Murray",
         "Title": "Blooming",
         "Station": "59th Street, Lexington Avenue (59th Street)",
         "Line": "IRT East Side Line",
         "Year": 1996
      },
      {
         "Artist": "Sarah Sze",
         "Title": "Blueprint for a Landscape",
         "Station": "96th Street",
         "Line": "2nd Avenue Subway",
         "Year": 2016
      },
      {
         "Artist": "Susan Morrison",
         "Title": "Borough Hall Station, First Subway In Brooklyn",
         "Station": "Borough Hall (East Side Branch)",
         "Line": "IRT Brooklyn Line",
         "Year": 2007
      },
      {
         "Artist": "",
         "Title": "Bowery Wall",
         "Station": "Whitehall Street",
         "Line": "BMT Broadway Line",
         "Year": null
      },
      {
         "Artist": "Susan Tunick",
         "Title": "Brighton Clay Re-Leaf",
         "Station": "Prospect Park, Parkside Avenue",
         "Line": "BMT Brighton Line",
         "Year": 1994
      },
      {
         "Artist": "Tim Snell",
         "Title": "Broadway Diary",
         "Station": "8th Street",
         "Line": "BMT Broadway Line",
         "Year": 2002
      },
      {
         "Artist": "Béatrice Coron",
         "Title": "Bronx Literature",
         "Station": "Burke Avenue",
         "Line": "IRT White Plains Road Line",
         "Year": 2006
      },
      {
         "Artist": "Barbara Grygutis",
         "Title": "Bronx River View",
         "Station": "Whitlock Avenue",
         "Line": "IRT Pelham Line",
         "Year": 2010
      },
      {
         "Artist": "Roy Secord",
         "Title": "Bronx Seasons Everchanging",
         "Station": "174th/175th Street",
         "Line": "IND Concourse Line",
         "Year": 2018
      },
      {
         "Artist": "Whitesavage/Lyle",
         "Title": "Bronx Trees",
         "Station": "Elder Avenue",
         "Line": "IRT Pelham Line",
         "Year": 2011
      },
      {
         "Artist": "Marina Tsesarskaya",
         "Title": "Bronx, Four Seasons",
         "Station": "Prospect Avenue",
         "Line": "IRT White Plains Road Line",
         "Year": 2006
      },
      {
         "Artist": "Priscila De Carvalho",
         "Title": "Bronx: Heart, Homeland",
         "Station": "Castle Hill Avenue",
         "Line": "IRT Pelham Line",
         "Year": 2015
      },
      {
         "Artist": "Ed Kopel",
         "Title": "Brooklyn Bucolic",
         "Station": "Avenue H",
         "Line": "BMT Brighton Line",
         "Year": 2012
      },
      {
         "Artist": "Jason Middlebrook",
         "Title": "Brooklyn Seeds",
         "Station": "Avenue U",
         "Line": "BMT Brighton Line",
         "Year": 2011
      },
      {
         "Artist": "Andrea Belag",
         "Title": "Brooklyn Transitions",
         "Station": "Avenue U",
         "Line": "BMT Culver Line",
         "Year": 2017
      },
      {
         "Artist": "Al Loving",
         "Title": "Brooklyn, New Morning",
         "Station": "Broadway Junction, Broadway-East New York (Broadway Junction), Broadway/East New York (Broadway Junction)",
         "Line": "BMT Canarsie Line",
         "Year": 2001
      },
      {
         "Artist": "Pat Steir",
         "Title": "Brueghel Series",
         "Station": "Eastern Parkway/Brooklyn Museum",
         "Line": "IRT Brooklyn Line",
         "Year": 1994
      },
      {
         "Artist": "Students of PS 126 and PS 20",
         "Title": "Buildings, Boats, and a Bridge",
         "Station": "Brooklyn Bridge/City Hall",
         "Line": "IRT East Side Line",
         "Year": null
      },
      {
         "Artist": "Mark Gibian",
         "Title": "Cable Crossing",
         "Station": "Brooklyn Bridge/City Hall",
         "Line": "IRT East Side Line",
         "Year": 1996
      },
      {
         "Artist": "Alexander Brodsky",
         "Title": "Canal Street Canal",
         "Station": "Canal Street",
         "Line": "BMT Broadway Line",
         "Year": 1997
      },
      {
         "Artist": "Josh Scharf",
         "Title": "Carnegie Hall Montage",
         "Station": "57th Street",
         "Line": "BMT Broadway Line",
         "Year": 1993
      },
      {
         "Artist": "Janet Zweig",
         "Title": "Carrying On",
         "Station": "Prince Street",
         "Line": "BMT Broadway Line",
         "Year": 2004
      },
      {
         "Artist": "Edward Del Rosario",
         "Title": "Centennial Game",
         "Station": "Subway Car Interior Art",
         "Line": "",
         "Year": 2004
      },
      {
         "Artist": "Karen Margolis",
         "Title": "Cerebration",
         "Station": "86th Street",
         "Line": "BMT Sea Beach Line",
         "Year": 2018
      },
      {
         "Artist": "Jennifer Cecere",
         "Title": "Chairs",
         "Station": "14th Street/Union Square",
         "Line": "IRT East Side Line",
         "Year": 1995
      },
      {
         "Artist": "Josie Gonzalez Albright",
         "Title": "Children at Play",
         "Station": "Woodlawn",
         "Line": "IRT Woodlawn Line",
         "Year": 2005
      },
      {
         "Artist": "Jimmy James Green",
         "Title": "Children's Cathedral",
         "Station": "Utica Avenue",
         "Line": "IND Fulton Street Line",
         "Year": 1996
      },
      {
         "Artist": "Ann Hamilton",
         "Title": "Chorus",
         "Station": "Cortlandt Street-World Trade Center",
         "Line": "IRT West Side Line",
         "Year": 2018
      },
      {
         "Artist": "Firelei Báez",
         "Title": "Ciguapa Antellana, me llamo sueño de la madrugada. (who more sci-fi than us)",
         "Station": "163rd Street/Amsterdam Avenue",
         "Line": "IND 8th Avenue Line",
         "Year": 2018
      },
      {
         "Artist": "Mark Hadjipateras",
         "Title": "City Dwellers",
         "Station": "28th Street",
         "Line": "BMT Broadway Line",
         "Year": 2002
      },
      {
         "Artist": "Chiho Aoshima",
         "Title": "City Glow",
         "Station": "14th Street/Union Square",
         "Line": "BMT Broadway Line",
         "Year": 2005
      },
      {
         "Artist": "Laura Bradley",
         "Title": "City Suite",
         "Station": "96th Street",
         "Line": "IRT East Side Line",
         "Year": 1994
      },
      {
         "Artist": "Romare Bearden",
         "Title": "City of Light",
         "Station": "Westchester Square",
         "Line": "IRT Pelham Line",
         "Year": 1993
      },
      {
         "Artist": "Ray Ring",
         "Title": "Clark Street Passage",
         "Station": "Clark Street",
         "Line": "IRT Brooklyn Line",
         "Year": 1987
      },
      {
         "Artist": "Sydney Cash",
         "Title": "Columns",
         "Station": "Queensborough Plaza",
         "Line": "IRT Flushing Line",
         "Year": 2000
      },
      {
         "Artist": "Emmett Wigglesworth",
         "Title": "CommUnion",
         "Station": "Union Street",
         "Line": "BMT 4th Avenue Line",
         "Year": 1994
      },
      {
         "Artist": "Alison Moritsugu",
         "Title": "Community (Acer rubrum, Rosa palustris, Smilax rotundifolia, Carya cordiformis)",
         "Station": "St. Lawrence Avenue",
         "Line": "IRT Pelham Line",
         "Year": 2011
      },
      {
         "Artist": "Andrea Deszö",
         "Title": "Community Garden",
         "Station": "Bedford Park Boulevard",
         "Line": "IRT Woodlawn Line",
         "Year": 2006
      },
      {
         "Artist": "John Cavanagh",
         "Title": "Commuting/Community",
         "Station": "61st Street/Woodside",
         "Line": "IRT Flushing Line",
         "Year": 1986
      },
      {
         "Artist": "Deborah Masters",
         "Title": "Coney Island Reliefs",
         "Station": "Ocean Parkway",
         "Line": "BMT Brighton Line",
         "Year": 1996
      },
      {
         "Artist": "Tim Zeltner",
         "Title": "Coney Island",
         "Station": "Subway Car Interior Art",
         "Line": "",
         "Year": null
      },
      {
         "Artist": "Ray King",
         "Title": "Connections",
         "Station": "Rockaway Boulevard",
         "Line": "IND Fulton Street Line",
         "Year": 2015
      },
      {
         "Artist": "Robert Hickman",
         "Title": "Convex Disk at Roosevelt Island",
         "Station": "Roosevelt Island",
         "Line": "IND 63rd Street Line",
         "Year": 1996
      },
      {
         "Artist": "Jill Parisi",
         "Title": "Coom Barooom",
         "Station": "Beach 44th Street/Frank Avenue",
         "Line": "IND Rockaway Line",
         "Year": 2011
      },
      {
         "Artist": "Michael Ingui",
         "Title": "Crescendo",
         "Station": "East 105th Street",
         "Line": "BMT Canarsie Line",
         "Year": 2007
      },
      {
         "Artist": "Schachter/Levi",
         "Title": "Cross-Bronx Waterway",
         "Station": "Middletown Road",
         "Line": "IRT Pelham Line",
         "Year": 2015
      },
      {
         "Artist": "Maureen McQuillan",
         "Title": "Crystal Blue Persuasion",
         "Station": "36th/Washington Aves.",
         "Line": "BMT Astoria Line",
         "Year": 2018
      },
      {
         "Artist": "Margaret Lanzetta",
         "Title": "Culture Swirl",
         "Station": "Norwood Avenue",
         "Line": "BMT Nassau Street-Jamaica Line",
         "Year": 2007
      },
      {
         "Artist": "Amy Pryor",
         "Title": "Day Into Night Into Day",
         "Station": "138th Street (Mott Haven)",
         "Line": "IRT Woodlawn Line",
         "Year": 2021
      },
      {
         "Artist": "Stephen T. Johnson",
         "Title": "DeKalb Improvisation",
         "Station": "DeKalb Avenue",
         "Line": "BMT 4th Avenue Line",
         "Year": 2004
      },
      {
         "Artist": "Ming Fay",
         "Title": "Delancey Orchard",
         "Station": "Delancey Street, Essex Street",
         "Line": "IND 6th Avenue Line",
         "Year": 2004
      },
      {
         "Artist": "Ben Snead",
         "Title": "Departures and Arrivals",
         "Station": "Jay St./Metrotech (Borough Hall)",
         "Line": "IND 8th Avenue Line",
         "Year": 2009
      },
      {
         "Artist": "Noel Copeland",
         "Title": "Displacing Details",
         "Station": "East Broadway",
         "Line": "IND 6th Avenue Line",
         "Year": 1992
      },
      {
         "Artist": "Laura F. Gibellini",
         "Title": "Dom (Variations)",
         "Station": "Seneca Avenue, Fresh Pond Road, Forest Avenue",
         "Line": "BMT Myrtle Avenue Line",
         "Year": 2014
      },
      {
         "Artist": "Chris Robinson",
         "Title": "Dream Train",
         "Station": "Gates Avenue",
         "Line": "BMT Nassau Street-Jamaica Line",
         "Year": 2002
      },
      {
         "Artist": "Monika Bravo",
         "Title": "Duration",
         "Station": "Prospect Avenue",
         "Line": "BMT 4th Avenue Line",
         "Year": 2017
      },
      {
         "Artist": "Saul Leiter",
         "Title": "Early Color",
         "Station": "42nd Street/Bryant Park",
         "Line": "IND 6th Avenue Line",
         "Year": 2007
      },
      {
         "Artist": "Sally Gil",
         "Title": "Edges of a South Brooklyn Sky",
         "Station": "Avenue U",
         "Line": "BMT Sea Beach Line",
         "Year": 2018
      },
      {
         "Artist": "Michael Kelly Williams",
         "Title": "El 2/El 5",
         "Station": "Intervale Avenue",
         "Line": "IRT White Plains Road Line",
         "Year": 1992
      },
      {
         "Artist": "Mara Held",
         "Title": "El in 16 Notes",
         "Station": "Hewes Street",
         "Line": "BMT Nassau Street-Jamaica Line",
         "Year": 2002
      },
      {
         "Artist": "Maria Dominguez",
         "Title": "El-Views",
         "Station": "Chauncey Street",
         "Line": "BMT Nassau Street-Jamaica Line",
         "Year": 2002
      },
      {
         "Artist": "Wopo Holup",
         "Title": "Elevated Nature I-IV",
         "Station": "207th Street, 215th Street, 225th Street, 231st Street",
         "Line": "IRT West Side Line",
         "Year": 1991
      },
      {
         "Artist": "Jean Shin",
         "Title": "Elevated",
         "Station": "Lexington Avenue-63rd Street",
         "Line": "IND 63rd Street Line",
         "Year": 2016
      },
      {
         "Artist": "Bing Lee",
         "Title": "Empress Voyage 2/27/1784",
         "Station": "Canal Street",
         "Line": "BMT Broadway Line",
         "Year": 1998
      },
      {
         "Artist": "Ronald Calloway",
         "Title": "Euphorbias",
         "Station": "Kosciuszko Street",
         "Line": "BMT Nassau Street-Jamaica Line",
         "Year": 2002
      },
      {
         "Artist": "Nick Cave",
         "Title": "Every One - Each One - Equal All",
         "Station": "Times Square/42nd Street",
         "Line": "IRT West Side Line",
         "Year": 2021
      },
      {
         "Artist": "Dan Sinclair",
         "Title": "Fast Track & Speed Wheels",
         "Station": "Grand Central",
         "Line": "IRT Times Square-Grand Central Shuttle",
         "Year": 1990
      },
      {
         "Artist": "Alyson Shotz",
         "Title": "Fathom Points + Compass Bearings",
         "Station": "Smith/9th Street",
         "Line": "IND Crosstown Line",
         "Year": 2013
      },
      {
         "Artist": "Philippe Lechien",
         "Title": "Fire Escape",
         "Station": "Subway Car Interior Art",
         "Line": "",
         "Year": 2008
      },
      {
         "Artist": "Kk Kozik",
         "Title": "First on the Beach - Wednesday Night Fireworks",
         "Station": "Rockaway Park/Beach 116th Street",
         "Line": "IND Rockaway Line",
         "Year": 2015
      },
      {
         "Artist": "Kathleen McCarthy",
         "Title": "Five Points of Observation",
         "Station": "102nd-104th Streets, Cypress Hills, Woodhaven Boulevard, 75th Street/Elderts Lane, 111th Street",
         "Line": "BMT Nassau Street-Jamaica Line",
         "Year": 1990
      },
      {
         "Artist": "Muriel Castanis",
         "Title": "Flatbush Floogies",
         "Station": "Flatbush Avenue",
         "Line": "IRT Brooklyn Line",
         "Year": 1996
      },
      {
         "Artist": "Emilio Perez",
         "Title": "Fluxus / Rythmus",
         "Station": "18th Avenue",
         "Line": "BMT Sea Beach Line",
         "Year": 2019
      },
      {
         "Artist": "Faith Ringgold",
         "Title": "Flying Home Harlem Heroes and Heroines",
         "Station": "125th Street",
         "Line": "IRT Lenox Avenue Line",
         "Year": 1996
      },
      {
         "Artist": "MTA Arts For Transit Collaborative",
         "Title": "For Want of a Nail",
         "Station": "81st Street/Museum of Natural History",
         "Line": "IND 8th Avenue Line",
         "Year": 1999
      },
      {
         "Artist": "Steve Wood",
         "Title": "Fossils",
         "Station": "137th Street/City College",
         "Line": "IRT West Side Line",
         "Year": 1988
      },
      {
         "Artist": "Mary Miss",
         "Title": "Framing Union Square",
         "Station": "14th Street/Union Square",
         "Line": "IRT East Side Line",
         "Year": 1998
      },
      {
         "Artist": "Cadence Giersbach",
         "Title": "From Earth To Sky",
         "Station": "Myrtle/Wyckoff Headhouse/Transfer, Myrtle Avenue",
         "Line": "BMT Myrtle Avenue Line",
         "Year": 2007
      },
      {
         "Artist": "Xenobia Bailey",
         "Title": "Funktional Vibrations",
         "Station": "34th Street-Hudson Yards",
         "Line": "IRT Flushing Line",
         "Year": 2015
      },
      {
         "Artist": "Jamal Ince",
         "Title": "Fusion",
         "Station": "Clinton/Washington Aves.",
         "Line": "IND Crosstown Line",
         "Year": 2000
      },
      {
         "Artist": "Andrea Deszö",
         "Title": "Garden Dwellers",
         "Station": "Subway Car Interior Art",
         "Line": "",
         "Year": 2009
      },
      {
         "Artist": "Patsy Norvell",
         "Title": "Garden Stops",
         "Station": "Beverley Road, Cortelyou Road",
         "Line": "BMT Brighton Line",
         "Year": 1994
      },
      {
         "Artist": "Eric Fischl",
         "Title": "Garden of Circus Delights",
         "Station": "34th Street/Penn Station",
         "Line": "IND 8th Avenue Line",
         "Year": 2001
      },
      {
         "Artist": "Jaime Arredondo",
         "Title": "Garden of Earthly Delights",
         "Station": "Zerega Avenue",
         "Line": "IRT Pelham Line",
         "Year": 2015
      },
      {
         "Artist": "Portia Munson",
         "Title": "Gardens of Fort Hamilton Parkway Station",
         "Station": "Fort Hamilton Parkway",
         "Line": "BMT West End Line",
         "Year": 2012
      },
      {
         "Artist": "George Bates",
         "Title": "Generation Dynamica",
         "Station": "Central Avenue",
         "Line": "BMT Myrtle Avenue Line",
         "Year": 2013
      },
      {
         "Artist": "Jorge Veras",
         "Title": "Ginger Heaven",
         "Station": "Borough Hall (East Side Branch)",
         "Line": "IRT Brooklyn Line",
         "Year": 1996
      },
      {
         "Artist": "Hugo Consuegra",
         "Title": "Good Morning, Good Night",
         "Station": "Utica Avenue",
         "Line": "IRT Brooklyn Line",
         "Year": 2004
      },
      {
         "Artist": "Marcos Chin",
         "Title": "Grand Central Catwalk",
         "Station": "Subway Car Interior Art",
         "Line": "",
         "Year": 2013
      },
      {
         "Artist": "Nicholas Pearson",
         "Title": "Halo",
         "Station": "34th Street/Herald Square",
         "Line": "IND 6th Avenue Line",
         "Year": 1991
      },
      {
         "Artist": "Peter Sis",
         "Title": "Happy City",
         "Station": "86th Street",
         "Line": "IRT East Side Line",
         "Year": 2004
      },
      {
         "Artist": "Ik-Joong Kang",
         "Title": "Happy World",
         "Station": "Main Street/Flushing",
         "Line": "IRT Flushing Line",
         "Year": 1998
      },
      {
         "Artist": "Rita MacDonald",
         "Title": "Hare Apparent",
         "Station": "Avenue M",
         "Line": "BMT Brighton Line",
         "Year": 2011
      },
      {
         "Artist": "Willie Birch",
         "Title": "Harlem Timeline",
         "Station": "135th Street",
         "Line": "IRT Lenox Avenue Line",
         "Year": 1995
      },
      {
         "Artist": "Soonae Tark",
         "Title": "Have a Happy Day",
         "Station": "Buhre Avenue",
         "Line": "IRT Pelham Line",
         "Year": 2015
      },
      {
         "Artist": "Sarah Morris",
         "Title": "Hellion Equilibrium",
         "Station": "39th/Beebe Aves.",
         "Line": "BMT Astoria Line",
         "Year": 2018
      },
      {
         "Artist": "NYC Artists & Public School Students",
         "Title": "Hello Columbus",
         "Station": "59th Street/Columbus Circle",
         "Line": "IND 8th Avenue Line",
         "Year": 1992
      },
      {
         "Artist": "Amy Bennett",
         "Title": "Heydays",
         "Station": "86th Street",
         "Line": "BMT 4th Avenue Line",
         "Year": 2011
      },
      {
         "Artist": "Jane Ingram Allen",
         "Title": "High Five",
         "Station": "42nd Street/Bryant Park",
         "Line": "IND 6th Avenue Line",
         "Year": 1994
      },
      {
         "Artist": "",
         "Title": "Historic New York Photographs",
         "Station": "Bowling Green",
         "Line": "IRT East Side Line",
         "Year": null
      },
      {
         "Artist": "Leo Villareal",
         "Title": "Hive",
         "Station": "Broadway/Lafayette, Bleecker Street",
         "Line": "IND 6th Avenue Line",
         "Year": 2012
      },
      {
         "Artist": "Joseph D'Alesandro",
         "Title": "Homage",
         "Station": "219th Street",
         "Line": "IRT White Plains Road Line",
         "Year": 2006
      },
      {
         "Artist": "Linda Ganjian",
         "Title": "Home Sweet Home",
         "Station": "111th Street-Greenwood Avenue",
         "Line": "IND Fulton Street Line",
         "Year": 2016
      },
      {
         "Artist": "George Trakas",
         "Title": "Hook, Line, and Sinker",
         "Station": "Atlantic Avenue",
         "Line": "IRT Brooklyn Line",
         "Year": 2004
      },
      {
         "Artist": "Laura Battle",
         "Title": "How to Get to the Moon",
         "Station": "Burnside Avenue",
         "Line": "IRT Woodlawn Line",
         "Year": 2006
      },
      {
         "Artist": "Tricia Keightley",
         "Title": "Hunters Point Avenue Project",
         "Station": "Hunters Point Avenue",
         "Line": "IRT Flushing Line",
         "Year": 2012
      },
      {
         "Artist": "Jeffrey Gibson",
         "Title": "I Am A Rainbow Too",
         "Station": "Astoria Boulevard/Hoyt Avenue",
         "Line": "BMT Astoria Line",
         "Year": 2019
      },
      {
         "Artist": "Jim Hodges",
         "Title": "I dreamed a world and called it love",
         "Station": "Grand Central",
         "Line": "IRT East Side Line",
         "Year": 2020
      },
      {
         "Artist": "Millie Burns",
         "Title": "IL7/Square",
         "Station": "Botanic Garden",
         "Line": "BMT Franklin Shuttle",
         "Year": 1999
      },
      {
         "Artist": "Robert Blackburn",
         "Title": "In Everything There is a Season",
         "Station": "116th Street",
         "Line": "IRT East Side Line",
         "Year": 2005
      },
      {
         "Artist": "Chris Gall",
         "Title": "In Flight",
         "Station": "Subway Car Interior Art",
         "Line": "",
         "Year": 2008
      },
      {
         "Artist": "Pablo Tauler",
         "Title": "In Memory of the Lost Battalion",
         "Station": "Woodhaven Boulevard/Queens Mall",
         "Line": "IND Queens Boulevard Line",
         "Year": 1996
      },
      {
         "Artist": "Esther Grillo",
         "Title": "In Search of Harmony Bay",
         "Station": "Howard Beach/JFK Airport",
         "Line": "IND Rockaway Line",
         "Year": 1992
      },
      {
         "Artist": "Francesco Simeti",
         "Title": "Indigenous-scapes",
         "Station": "4th Avenue",
         "Line": "IND Crosstown Line",
         "Year": 2016
      },
      {
         "Artist": "Cara Lynch",
         "Title": "Inheritance: In Memory of American Glass",
         "Station": "Ditmas Avenue",
         "Line": "BMT Culver Line",
         "Year": 2017
      },
      {
         "Artist": "Dan Zeller",
         "Title": "Internal Connectivity",
         "Station": "Bay 50th Street",
         "Line": "BMT West End Line",
         "Year": 2012
      },
      {
         "Artist": "Sam Gilliam",
         "Title": "Jamaica Center Station Riders, Blue",
         "Station": "Jamaica Center/Parsons-Archer",
         "Line": "IND Queens Boulevard Line",
         "Year": 1991
      },
      {
         "Artist": "Verna Hart",
         "Title": "Jammin' Under the El",
         "Station": "Myrtle Avenue",
         "Line": "BMT Nassau Street-Jamaica Line",
         "Year": 1999
      },
      {
         "Artist": "Odili Donald Odita",
         "Title": "Kaleidoscope",
         "Station": "20th Avenue",
         "Line": "BMT West End Line",
         "Year": 2012
      },
      {
         "Artist": "Rhoda Yohai Andors",
         "Title": "Kings Highway Hieroglyphics",
         "Station": "Kings Highway",
         "Line": "BMT Brighton Line",
         "Year": 1987
      },
      {
         "Artist": "Robert Hickman",
         "Title": "Laced Canopy (Verdi's Rigoletto)",
         "Station": "72nd Street",
         "Line": "IRT West Side Line",
         "Year": 2005
      },
      {
         "Artist": "James Garvey",
         "Title": "Lariat Seat Loops",
         "Station": "33rd Street, Wall Street",
         "Line": "IRT East Side Line",
         "Year": 1997
      },
      {
         "Artist": "Amy Cheng",
         "Title": "Las Flores",
         "Station": "Cleveland Street",
         "Line": "BMT Nassau Street-Jamaica Line",
         "Year": 2007
      },
      {
         "Artist": "George Crespo",
         "Title": "Latin American Stories",
         "Station": "Jackson Avenue",
         "Line": "IRT White Plains Road Line",
         "Year": 2006
      },
      {
         "Artist": "Noel Copeland",
         "Title": "Leaf of Life",
         "Station": "238th Street (Nereid Avenue)",
         "Line": "IRT White Plains Road Line",
         "Year": 2006
      },
      {
         "Artist": "Tom Otterness",
         "Title": "Life Underground",
         "Station": "14th Street, 8th Avenue",
         "Line": "IND 8th Avenue Line",
         "Year": 2000
      },
      {
         "Artist": "Eric Pryor",
         "Title": "Life and Continued Growth",
         "Station": "Franklin Avenue",
         "Line": "BMT Franklin Shuttle",
         "Year": 1999
      },
      {
         "Artist": "",
         "Title": "Live the Dream",
         "Station": "East 177th Street/Parkchester",
         "Line": "IRT Pelham Line",
         "Year": null
      },
      {
         "Artist": "James Gulliver Hancock",
         "Title": "Living in New York",
         "Station": "Subway Car Interior Art",
         "Line": "",
         "Year": 2014
      },
      {
         "Artist": "Valerie Jaudon",
         "Title": "Long Division",
         "Station": "23rd Street",
         "Line": "IRT East Side Line",
         "Year": 1988
      },
      {
         "Artist": "Ellen Harvey",
         "Title": "Look Up Not Down",
         "Station": "Queens Plaza",
         "Line": "IND Queens Boulevard Line",
         "Year": 2005
      },
      {
         "Artist": "Michael Krondl",
         "Title": "Looking Up",
         "Station": "Neptune Avenue",
         "Line": "BMT Culver Line",
         "Year": 2004
      },
      {
         "Artist": "Lisa Dinhofer",
         "Title": "Losing My Marbles",
         "Station": "42nd Street/Port Authority Bus Terminal",
         "Line": "IND 8th Avenue Line",
         "Year": 2003
      },
      {
         "Artist": "Haresh Lalvani",
         "Title": "MORPHING88",
         "Station": "88th Street-Boyd Avenue",
         "Line": "IND Fulton Street Line",
         "Year": 2015
      },
      {
         "Artist": "Jennifer Kotter",
         "Title": "MTA Jewels",
         "Station": "6th Avenue",
         "Line": "BMT Canarsie Line",
         "Year": 1993
      },
      {
         "Artist": "Olalekan Jeyifous",
         "Title": "Made With Love",
         "Station": "8th Avenue",
         "Line": "BMT Sea Beach Line",
         "Year": 2019
      },
      {
         "Artist": "Felipe Galindo",
         "Title": "Magic Realism in Kingsbridge",
         "Station": "231st Street",
         "Line": "IRT West Side Line",
         "Year": 2007
      },
      {
         "Artist": "José Ortiz",
         "Title": "Many Trails",
         "Station": "183rd Street",
         "Line": "IRT Woodlawn Line",
         "Year": 2006
      },
      {
         "Artist": "Frederick Dana Marsh",
         "Title": "Marine Grill Murals, 1913",
         "Station": "Fulton Street (Broadway/Nassau), Fulton Street",
         "Line": "IND 8th Avenue Line",
         "Year": 2000
      },
      {
         "Artist": "Bill Brand",
         "Title": "Masstransiscope",
         "Station": "Myrtle Avenue",
         "Line": "BMT 4th Avenue Line",
         "Year": 1980
      },
      {
         "Artist": "Keith Godard",
         "Title": "Memories of Twenty-Third Street",
         "Station": "23rd Street",
         "Line": "BMT Broadway Line",
         "Year": 2002
      },
      {
         "Artist": "John Woodrow Kelley",
         "Title": "Mercury",
         "Station": "Clinton/Washington Aves.",
         "Line": "IND Crosstown Line",
         "Year": 2000
      },
      {
         "Artist": "Dan George",
         "Title": "Mermade/Dionysus and the Pirates",
         "Station": "Brighton Beach",
         "Line": "BMT Brighton Line",
         "Year": 1999
      },
      {
         "Artist": "Maren Hassinger",
         "Title": "Message from Malcolm",
         "Station": "110th Street/Central Park North",
         "Line": "IRT Lenox Avenue Line",
         "Year": 1998
      },
      {
         "Artist": "Corinne Grondahl",
         "Title": "Metromorphosis/Birth of a Station",
         "Station": "Mosholu Parkway",
         "Line": "IRT Woodlawn Line",
         "Year": 2006
      },
      {
         "Artist": "Alex Katz",
         "Title": "Metropolitan Faces",
         "Station": "57th Street",
         "Line": "IND 6th Avenue Line",
         "Year": 2018
      },
      {
         "Artist": "Andrea Arroyo",
         "Title": "Mi Sol, Mi Planeta, Mi Ciudad (My Sun, My Planet, My City)",
         "Station": "Gun Hill Road",
         "Line": "IRT White Plains Road Line",
         "Year": 2006
      },
      {
         "Artist": "Christopher Wynter",
         "Title": "Migrations",
         "Station": "110th Street/Cathedral Parkway",
         "Line": "IND 8th Avenue Line",
         "Year": 1999
      },
      {
         "Artist": "Robin Holder",
         "Title": "Migrations",
         "Station": "Flushing Avenue",
         "Line": "BMT Nassau Street-Jamaica Line",
         "Year": 2006
      },
      {
         "Artist": "Josh Dorman",
         "Title": "Minor Landscape",
         "Station": "Clinton/Washington Aves.",
         "Line": "IND Crosstown Line",
         "Year": null
      },
      {
         "Artist": "Vincent Smith",
         "Title": "Minton's Playhouse/Movers and Shakers",
         "Station": "116th Street",
         "Line": "IRT Lenox Avenue Line",
         "Year": 1999
      },
      {
         "Artist": "Sophie Blackall",
         "Title": "Missed Connections",
         "Station": "Subway Car Interior Art",
         "Line": "",
         "Year": 2012
      },
      {
         "Artist": "",
         "Title": "MoMA Atlantic/Pacific",
         "Station": "Pacific Street (Atlantic Avenue–Barclays Center), Atlantic Avenue, Atlantic Avenue",
         "Line": "BMT 4th Avenue Line",
         "Year": 2009
      },
      {
         "Artist": "Robert Wilson",
         "Title": "My Coney Island Baby",
         "Station": "Coney Island/Stillwell Avenue",
         "Line": "BMT West End Line",
         "Year": 2004
      },
      {
         "Artist": "Andrea Deszö",
         "Title": "Nature Rail",
         "Station": "62nd Street",
         "Line": "BMT West End Line",
         "Year": 2012
      },
      {
         "Artist": "Andrea Deszö",
         "Title": "Nature Wall",
         "Station": "New Utrecht Avenue",
         "Line": "BMT Sea Beach Line",
         "Year": 2018
      },
      {
         "Artist": "Alyson Shotz",
         "Title": "Nautical Charts, Gowanus and Red Hook, 1733-1922",
         "Station": "Smith/9th Street",
         "Line": "IND Crosstown Line",
         "Year": 2013
      },
      {
         "Artist": "Nitza Tufino",
         "Title": "Neo-Boriken",
         "Station": "103rd Street",
         "Line": "IRT East Side Line",
         "Year": 1990
      },
      {
         "Artist": "Leslie Wayne",
         "Title": "Neptune's Garden",
         "Station": "Bay Parkway (22nd Avenue)",
         "Line": "BMT Culver Line",
         "Year": 2018
      },
      {
         "Artist": "MTA Arts For Transit Collaborative",
         "Title": "New York City Architectural Artifacts from the Collection of the Brooklyn Museum",
         "Station": "Eastern Parkway/Brooklyn Museum",
         "Line": "IRT Brooklyn Line",
         "Year": 2004
      },
      {
         "Artist": "Edith Kramer",
         "Title": "New York Subway Station",
         "Station": "Spring Street",
         "Line": "IND 8th Avenue Line",
         "Year": 1994
      },
      {
         "Artist": "Jacob Lawrence",
         "Title": "New York in Transit",
         "Station": "Times Square/42nd Street",
         "Line": "IRT West Side Line",
         "Year": 2001
      },
      {
         "Artist": "Jim Porter",
         "Title": "Night and Day",
         "Station": "Clinton/Washington Aves.",
         "Line": "IND Crosstown Line",
         "Year": 1998
      },
      {
         "Artist": "Marcel Dzama",
         "Title": "No Less Than Everything Comes Together",
         "Station": "Bedford Avenue",
         "Line": "BMT Canarsie Line",
         "Year": 2021
      },
      {
         "Artist": "Jones/Ginzel/Piras",
         "Title": "Oculus",
         "Station": "Chambers Street/World Trade Center, Park Place",
         "Line": "IND 8th Avenue Line",
         "Year": 1998
      },
      {
         "Artist": "Ingo Fast",
         "Title": "On and Off the Boardwalk",
         "Station": "Beach 67th Street/Gaston Avenue",
         "Line": "IND Rockaway Line",
         "Year": 2011
      },
      {
         "Artist": "Béatrice Coron",
         "Title": "On the Right Track",
         "Station": "104th Street-Oxford Ave.",
         "Line": "IND Fulton Street Line",
         "Year": 2015
      },
      {
         "Artist": "Houston Conwill",
         "Title": "Open Secret",
         "Station": "125th Street",
         "Line": "IRT East Side Line",
         "Year": 1986
      },
      {
         "Artist": "Raúl Colón",
         "Title": "Our Cup of Tea",
         "Station": "",
         "Line": "",
         "Year": 2002
      },
      {
         "Artist": "Reginald Polynice",
         "Title": "Our Spectrum of Support",
         "Station": "179th Street",
         "Line": "IND Queens Boulevard Line",
         "Year": 1993
      },
      {
         "Artist": "Diane Carr",
         "Title": "Outlook",
         "Station": "Broadway",
         "Line": "BMT Astoria Line",
         "Year": 2018
      },
      {
         "Artist": "Allen & Ellen Wexler",
         "Title": "Overlook",
         "Station": "Atlantic Terminal (Flatbush Avenue)",
         "Line": "LIRR Flatbush Avenue Line",
         "Year": 2009
      },
      {
         "Artist": "Derek Fordjour",
         "Title": "Parade",
         "Station": "145th Street",
         "Line": "IRT Lenox Avenue Line",
         "Year": 2018
      },
      {
         "Artist": "Chiho Aoshima",
         "Title": "Paradise",
         "Station": "14th Street/Union Square",
         "Line": "IRT East Side Line",
         "Year": 2005
      },
      {
         "Artist": "Ross Lewis",
         "Title": "Parallel Motion",
         "Station": "14th Street, 8th Avenue",
         "Line": "IND 8th Avenue Line",
         "Year": 1989
      },
      {
         "Artist": "Joyce Kozloff",
         "Title": "Parkside Portals",
         "Station": "86th Street",
         "Line": "IND 8th Avenue Line",
         "Year": 2018
      },
      {
         "Artist": "Tom Patti",
         "Title": "Passage",
         "Station": "74th Street/Broadway",
         "Line": "IRT Flushing Line",
         "Year": 2004
      },
      {
         "Artist": "Frank Giorgini",
         "Title": "Passages",
         "Station": "Whitehall Street",
         "Line": "BMT Broadway Line",
         "Year": 2000
      },
      {
         "Artist": "Al Held",
         "Title": "Passing Through",
         "Station": "Lexington Avenue-53rd Street, 51st Street",
         "Line": "IND Queens Boulevard Line",
         "Year": 2004
      },
      {
         "Artist": "Mauricio Lopez",
         "Title": "Past/Present/Future",
         "Station": "Beach 25th Street/Wavecrest",
         "Line": "IND Rockaway Line",
         "Year": 2011
      },
      {
         "Artist": "Moses Ros",
         "Title": "Patriasana, Wholesomeland",
         "Station": "Fordham Road",
         "Line": "IRT Woodlawn Line",
         "Year": 2005
      },
      {
         "Artist": "Eamon Ore-Giron",
         "Title": "People's Instinctive Travels: Homage to The Tribe",
         "Station": "Bay Parkway (22nd Avenue)",
         "Line": "BMT Sea Beach Line",
         "Year": 2018
      },
      {
         "Artist": "Stephen Westfall",
         "Title": "Perasma I and II",
         "Station": "30th/Grand Aves.",
         "Line": "BMT Astoria Line",
         "Year": 2018
      },
      {
         "Artist": "Vik Muniz",
         "Title": "Perfect Strangers",
         "Station": "72nd Street",
         "Line": "2nd Avenue Subway",
         "Year": 2016
      },
      {
         "Artist": "Alfredo Ceibal",
         "Title": "Permanent Residents and Visitors",
         "Station": "241st Street",
         "Line": "IRT White Plains Road Line",
         "Year": 2006
      },
      {
         "Artist": "Deborah Brown",
         "Title": "Platform Diving",
         "Station": "Houston Street",
         "Line": "IRT West Side Line",
         "Year": 1994
      },
      {
         "Artist": "Valerie Maynard",
         "Title": "Polyrhythmics of Consciousness and Light",
         "Station": "125th Street",
         "Line": "IRT East Side Line",
         "Year": 2002
      },
      {
         "Artist": "DeBorah Goletz",
         "Title": "Postcards From Sheepshead Bay",
         "Station": "Sheepshead Bay",
         "Line": "BMT Brighton Line",
         "Year": 1997
      },
      {
         "Artist": "Raúl Colón",
         "Title": "Primavera",
         "Station": "191st Street",
         "Line": "IRT West Side Line",
         "Year": 2003
      },
      {
         "Artist": "Lisa Sigal",
         "Title": "Push Pull",
         "Station": "Avenue N",
         "Line": "BMT Culver Line",
         "Year": 2018
      },
      {
         "Artist": "Yumi Heo",
         "Title": "Q is For Queens",
         "Station": "33rd Street/Rawson Street, 40th Street/Lowery Street, 46th Street/Bliss Street",
         "Line": "IRT Flushing Line",
         "Year": 1999
      },
      {
         "Artist": "Katherine Bradford",
         "Title": "Queens of the Night",
         "Station": "1st Avenue",
         "Line": "BMT Canarsie Line",
         "Year": 2021
      },
      {
         "Artist": "Christopher Janney",
         "Title": "REACH New York, An Urban Musical Instrument",
         "Station": "34th Street/Herald Square",
         "Line": "BMT Broadway Line",
         "Year": 1996
      },
      {
         "Artist": "Dave Calver",
         "Title": "Rabbit Transit (unofficial name)",
         "Station": "Subway Car Interior Art",
         "Line": "",
         "Year": 2006
      },
      {
         "Artist": "Michele Oka Doner",
         "Title": "Radiant Site",
         "Station": "34th Street/Herald Square",
         "Line": "BMT Broadway Line",
         "Year": 1991
      },
      {
         "Artist": "Michelle Greene",
         "Title": "Railrider's Throne",
         "Station": "116th Street/Columbia University",
         "Line": "IRT West Side Line",
         "Year": 1991
      },
      {
         "Artist": "Juan Sanchez",
         "Title": "Reaching Out For Each Other",
         "Station": "176th Street",
         "Line": "IRT Woodlawn Line",
         "Year": 2006
      },
      {
         "Artist": "John Blackford",
         "Title": "Redbird In Air",
         "Station": "Subway Car Interior Art",
         "Line": "",
         "Year": null
      },
      {
         "Artist": "Amy Cheng",
         "Title": "Rediscovery",
         "Station": "25th Avenue",
         "Line": "BMT West End Line",
         "Year": 2012
      },
      {
         "Artist": "Jason Rohlf",
         "Title": "Respite",
         "Station": "Mott Avenue/Far Rockaway",
         "Line": "IND Rockaway Line",
         "Year": 2011
      },
      {
         "Artist": "Kiki Smith",
         "Title": "River Light/The Water's Way/The Presence/The Spring/The Sound",
         "Station": "Grand Central Madison",
         "Line": "LIRR Main Line",
         "Year": 2022
      },
      {
         "Artist": "Wopo Holup",
         "Title": "River to River",
         "Station": "125th Street",
         "Line": "IRT West Side Line",
         "Year": 1991
      },
      {
         "Artist": "Nancy Blum",
         "Title": "Roaming Underfoot",
         "Station": "28th Street",
         "Line": "IRT East Side Line",
         "Year": 2019
      },
      {
         "Artist": "Susan Farrington",
         "Title": "Robots",
         "Station": "Subway Car Interior Art",
         "Line": "",
         "Year": 2014
      },
      {
         "Artist": "Annette Davidek",
         "Title": "Roundlet Series",
         "Station": "Lorimer Street",
         "Line": "BMT Nassau Street-Jamaica Line",
         "Year": 2002
      },
      {
         "Artist": "Yoko Ono",
         "Title": "SKY",
         "Station": "72nd Street",
         "Line": "IND 8th Avenue Line",
         "Year": 2018
      },
      {
         "Artist": "Danny Simmons",
         "Title": "Safe Passage",
         "Station": "Clinton/Washington Aves.",
         "Line": "IND Crosstown Line",
         "Year": null
      },
      {
         "Artist": "David Storey",
         "Title": "Sea City Spin",
         "Station": "20th Avenue",
         "Line": "BMT Sea Beach Line",
         "Year": 2019
      },
      {
         "Artist": "Philemona Williamson",
         "Title": "Seasons",
         "Station": "Livonia Avenue",
         "Line": "BMT Canarsie Line",
         "Year": 2007
      },
      {
         "Artist": "Skowmon Hastanan",
         "Title": "Secret Garden: There's No Place Like Home",
         "Station": "233rd Street",
         "Line": "IRT White Plains Road Line",
         "Year": 2006
      },
      {
         "Artist": "Doug & Mike Starn",
         "Title": "See It Split, See It Change",
         "Station": "South Ferry (New Station)",
         "Line": "IRT West Side Line",
         "Year": 2007
      },
      {
         "Artist": "Ming Fay",
         "Title": "Shad Crossing",
         "Station": "Delancey Street, Essex Street",
         "Line": "IND 6th Avenue Line",
         "Year": 2004
      },
      {
         "Artist": "Mel Chin",
         "Title": "Signal",
         "Station": "Broadway/Lafayette, Bleecker Street",
         "Line": "IND 6th Avenue Line",
         "Year": 1998
      },
      {
         "Artist": "Jackie Chang",
         "Title": "Signs of Life",
         "Station": "Metropolitan Avenue/Grand Street",
         "Line": "IND Crosstown Line",
         "Year": 2000
      },
      {
         "Artist": "James Carpenter Design Associates, Grimshaw Archit",
         "Title": "Sky Reflector-Net",
         "Station": "Fulton Street Transit Center",
         "Line": "IRT East Side Line",
         "Year": 2014
      },
      {
         "Artist": "Gwynne Duncan",
         "Title": "Smith & 9th",
         "Station": "Clinton/Washington Aves.",
         "Line": "IND Crosstown Line",
         "Year": 1998
      },
      {
         "Artist": "Mia Pearlman",
         "Title": "Soar",
         "Station": "80th Street-Hudson Street",
         "Line": "IND Fulton Street Line",
         "Year": 2015
      },
      {
         "Artist": "Sandra Bloodworth",
         "Title": "South Sails",
         "Station": "South Ferry (Outer Loop Station)",
         "Line": "IRT West Side Line",
         "Year": 1990
      },
      {
         "Artist": "Luisa Caldwell",
         "Title": "Station Villa",
         "Station": "East 180th Street",
         "Line": "IRT White Plains Road Line",
         "Year": 2011
      },
      {
         "Artist": "William Wegman",
         "Title": "Stationary Figures",
         "Station": "23rd Street",
         "Line": "IND 6th Avenue Line",
         "Year": 2018
      },
      {
         "Artist": "Tim Connor",
         "Title": "Steps to the Subway",
         "Station": "Atlantic Avenue",
         "Line": "IRT Brooklyn Line",
         "Year": null
      },
      {
         "Artist": "Katy Fischer",
         "Title": "Strata",
         "Station": "Bay Ridge Avenue",
         "Line": "BMT 4th Avenue Line",
         "Year": 2017
      },
      {
         "Artist": "Elizabeth Murray",
         "Title": "Stream",
         "Station": "Court Square/23rd St (Ely Avenue)",
         "Line": "IND Queens Boulevard Line",
         "Year": 2001
      },
      {
         "Artist": "Owen Smith",
         "Title": "Subway Builders",
         "Station": "Subway Car Interior Art",
         "Line": "",
         "Year": null
      },
      {
         "Artist": "Tanen/Hagen",
         "Title": "Subway Chicks",
         "Station": "Subway Car Interior Art",
         "Line": "",
         "Year": 2004
      },
      {
         "Artist": "Chuck Close",
         "Title": "Subway Portraits",
         "Station": "86th Street",
         "Line": "2nd Avenue Subway",
         "Year": 2016
      },
      {
         "Artist": "Ralph Fasanella",
         "Title": "Subway Riders",
         "Station": "5th Avenue/53rd Street",
         "Line": "IND Queens Boulevard Line",
         "Year": 1950
      },
      {
         "Artist": "Harry Roseman",
         "Title": "Subway Wall",
         "Station": "Wall Street",
         "Line": "IRT West Side Line",
         "Year": 1990
      },
      {
         "Artist": "Peter Sis",
         "Title": "Subway Whale",
         "Station": "Subway Car Interior Art",
         "Line": "",
         "Year": 2001
      },
      {
         "Artist": "Michael Miller",
         "Title": "Surf Station 90",
         "Station": "Beach 90th Street/Holland",
         "Line": "IND Rockaway Line",
         "Year": 2011
      },
      {
         "Artist": "George Bates",
         "Title": "Symphonic Convergence 1 & 2",
         "Station": "Beach 36th Street/Edgemere",
         "Line": "IND Rockaway Line",
         "Year": 2011
      },
      {
         "Artist": "Frank Olt",
         "Title": "Temple Quad Reliefs",
         "Station": "Court Square/23rd St (Ely Avenue)",
         "Line": "IND Queens Boulevard Line",
         "Year": 1992
      },
      {
         "Artist": "Diana Al-Hadid",
         "Title": "The Arches of Old Penn Station; The Arc of Gradiva",
         "Station": "34th Street/Penn Station",
         "Line": "IRT West Side Line",
         "Year": 2018
      },
      {
         "Artist": "Simon Levenson",
         "Title": "The Beaches of New York City",
         "Station": "Beach 60th Street/Straiton",
         "Line": "IND Rockaway Line",
         "Year": 2011
      },
      {
         "Artist": "Norman B. Colp",
         "Title": "The Commuter's Lament/A Close Shave",
         "Station": "42nd Street/Port Authority Bus Terminal",
         "Line": "IND 8th Avenue Line",
         "Year": 1991
      },
      {
         "Artist": "Cal Lane",
         "Title": "The Digs",
         "Station": "Knickerbocker Avenue",
         "Line": "BMT Myrtle Avenue Line",
         "Year": 2014
      },
      {
         "Artist": "Sameeh Alderazi",
         "Title": "The Dream",
         "Station": "Clinton/Washington Aves.",
         "Line": "IND Crosstown Line",
         "Year": 2000
      },
      {
         "Artist": "Daniel Hauben",
         "Title": "The El",
         "Station": "Freeman Street",
         "Line": "IRT White Plains Road Line",
         "Year": 2005
      },
      {
         "Artist": "Nicole Bengiveno",
         "Title": "The Essence of Time",
         "Station": "Bowling Green",
         "Line": "IRT East Side Line",
         "Year": 2007
      },
      {
         "Artist": "Joan Linder",
         "Title": "The Flora of Bensonhurst",
         "Station": "71st Street",
         "Line": "BMT West End Line",
         "Year": 2012
      },
      {
         "Artist": "Christo",
         "Title": "The Gates",
         "Station": "5th Avenue",
         "Line": "BMT Broadway Line",
         "Year": 2004
      },
      {
         "Artist": "Lee Brozgol",
         "Title": "The Greenwich Village Murals",
         "Station": "Christopher Street/Sheridan Square",
         "Line": "IRT West Side Line",
         "Year": 1994
      },
      {
         "Artist": "Takayo Noda",
         "Title": "The Habitat for the Yellow Bird",
         "Station": "Sutter Avenue",
         "Line": "BMT Canarsie Line",
         "Year": 2007
      },
      {
         "Artist": "Cristalli/Brown",
         "Title": "The Land Between Two Waters",
         "Station": "Morrison/Soundview Aves.",
         "Line": "IRT Pelham Line",
         "Year": 2010
      },
      {
         "Artist": "Amir Bey",
         "Title": "The Procession of Folk, No. 3",
         "Station": "Mt. Eden Avenue",
         "Line": "IRT Woodlawn Line",
         "Year": 2006
      },
      {
         "Artist": "Jack Beal",
         "Title": "The Return of Spring/The Onset of Winter",
         "Station": "Times Square/42nd Street",
         "Line": "IRT West Side Line",
         "Year": 1999
      },
      {
         "Artist": "Jane Dickson",
         "Title": "The Revelers",
         "Station": "Times Square/42nd Street",
         "Line": "IRT West Side Line",
         "Year": 2007
      },
      {
         "Artist": "W. P. Snyder",
         "Title": "The Sixth Avenue Elevated, 1878",
         "Station": "42nd Street/Bryant Park",
         "Line": "IND 6th Avenue Line",
         "Year": null
      },
      {
         "Artist": "R. Gregory Christie",
         "Title": "The Subway Soiree",
         "Station": "Subway Car Interior Art",
         "Line": "",
         "Year": 2012
      },
      {
         "Artist": "MTA Arts & Design and The Museum of Modern Art",
         "Title": "The Subway: Design for a Modern Icon",
         "Station": "5th Avenue/53rd Street",
         "Line": "IND Queens Boulevard Line",
         "Year": 2020
      },
      {
         "Artist": "Diana Al-Hadid",
         "Title": "The Time Telling",
         "Station": "34th Street/Penn Station",
         "Line": "IRT West Side Line",
         "Year": null
      },
      {
         "Artist": "Duke Riley",
         "Title": "The U Line",
         "Station": "Subway Car Interior Art",
         "Line": "",
         "Year": 2010
      },
      {
         "Artist": "Barbara Ellmann",
         "Title": "The View From Here",
         "Station": "Van Siclen Avenue",
         "Line": "BMT Nassau Street-Jamaica Line",
         "Year": 2007
      },
      {
         "Artist": "Maria Berrio",
         "Title": "There is Magic Underneath it All",
         "Station": "Fort Hamilton Parkway",
         "Line": "BMT Sea Beach Line",
         "Year": 2019
      },
      {
         "Artist": "Roy Lichtenstein",
         "Title": "Times Square Mural",
         "Station": "Times Square/42nd Street",
         "Line": "IRT West Side Line",
         "Year": 1994
      },
      {
         "Artist": "Toby Buonagurio",
         "Title": "Times Square Times: 35 Times",
         "Station": "Times Square/42nd Street",
         "Line": "IRT West Side Line",
         "Year": 2005
      },
      {
         "Artist": "Max Neuhaus",
         "Title": "Times Square, 1977-1992",
         "Station": "Times Square/42nd Street",
         "Line": "IRT West Side Line",
         "Year": 2002
      },
      {
         "Artist": "",
         "Title": "Title unknown",
         "Station": "Sterling Street",
         "Line": "IRT Brooklyn Line",
         "Year": null
      },
      {
         "Artist": "",
         "Title": "Title unknown",
         "Station": "242nd Street/Van Cortlandt Park",
         "Line": "IRT West Side Line",
         "Year": 2007
      },
      {
         "Artist": "",
         "Title": "Title unknown",
         "Station": "Grand Central",
         "Line": "IRT East Side Line",
         "Year": null
      },
      {
         "Artist": "",
         "Title": "Title unknown",
         "Station": "191st Street",
         "Line": "IRT West Side Line",
         "Year": 2008
      },
      {
         "Artist": "",
         "Title": "Title unknown",
         "Station": "Westchester Square",
         "Line": "IRT Pelham Line",
         "Year": null
      },
      {
         "Artist": "James Gulliver Hancock",
         "Title": "Title unknown",
         "Station": "Subway Car Interior Art",
         "Line": "",
         "Year": 2017
      },
      {
         "Artist": "Student Artists",
         "Title": "Title unknown",
         "Station": "Clinton/Washington Aves.",
         "Line": "IND Crosstown Line",
         "Year": 1986
      },
      {
         "Artist": "Jenna Lucente",
         "Title": "Tottenville Sun, Tottenville Sky",
         "Station": "Arthur Kill",
         "Line": "SIRT",
         "Year": 2016
      },
      {
         "Artist": "Margie Hughto",
         "Title": "Trade, Treasure, and Travel",
         "Station": "Cortlandt Street-World Trade Center",
         "Line": "BMT Broadway Line",
         "Year": 1997
      },
      {
         "Artist": "Gardner/Heller",
         "Title": "Trains of Thought",
         "Station": "Grand Street",
         "Line": "IND 6th Avenue Line",
         "Year": null
      },
      {
         "Artist": "David Wilson",
         "Title": "Transit Skylight",
         "Station": "Newkirk Plaza",
         "Line": "BMT Brighton Line",
         "Year": 1998
      },
      {
         "Artist": "Louis Delsarte",
         "Title": "Transitions",
         "Station": "Church Avenue",
         "Line": "IRT Brooklyn Line",
         "Year": 2001
      },
      {
         "Artist": "Takayo Noda",
         "Title": "Traveling Dinosaur Chicks",
         "Station": "Subway Car Interior Art",
         "Line": "",
         "Year": 2011
      },
      {
         "Artist": "Jackie Battenfield",
         "Title": "Tree Canopy",
         "Station": "Avenue P",
         "Line": "BMT Culver Line",
         "Year": 2018
      },
      {
         "Artist": "Xin Song",
         "Title": "Tree of Life",
         "Station": "Bay Parkway",
         "Line": "BMT West End Line",
         "Year": 2012
      },
      {
         "Artist": "Nina Yankowitz",
         "Title": "Tunnel Vision",
         "Station": "51st Street",
         "Line": "IRT East Side Line",
         "Year": 1989
      },
      {
         "Artist": "Manuel Vega",
         "Title": "Un Sabado en la Ciento Diez (A Saturday on 110th Street)",
         "Station": "110th Street",
         "Line": "IRT East Side Line",
         "Year": 1996
      },
      {
         "Artist": "José Ortega",
         "Title": "Una Raza, Un Mundo, Universo (One Race, One World, One Universe)",
         "Station": "3rd Avenue/149th Street",
         "Line": "IRT White Plains Road Line",
         "Year": 1996
      },
      {
         "Artist": "Samm Kunce",
         "Title": "Under Bryant Park",
         "Station": "42nd Street/Bryant Park, 5th Avenue",
         "Line": "IND 6th Avenue Line",
         "Year": 2002
      },
      {
         "Artist": "Travis Ruse",
         "Title": "Underground Exposure: Photographs from a Daily Commute",
         "Station": "42nd Street/Bryant Park, Atlantic Avenue",
         "Line": "IND 6th Avenue Line",
         "Year": 2010
      },
      {
         "Artist": "Krystyna Spisak-Madejczyk",
         "Title": "Underground Skies/Cloud Forest",
         "Station": "Union Turnpike/Kew Gardens",
         "Line": "IND Queens Boulevard Line",
         "Year": null
      },
      {
         "Artist": "Alena Ort",
         "Title": "Underground Sky",
         "Station": "Bowling Green",
         "Line": "IRT East Side Line",
         "Year": null
      },
      {
         "Artist": "Isha Shabaka",
         "Title": "Units of the Free",
         "Station": "Park Place",
         "Line": "BMT Franklin Shuttle",
         "Year": 1999
      },
      {
         "Artist": "Nicky Enright",
         "Title": "Universal City",
         "Station": "225th Street",
         "Line": "IRT White Plains Road Line",
         "Year": 2006
      },
      {
         "Artist": "Milton Glaser",
         "Title": "Untitled",
         "Station": "Astor Place",
         "Line": "IRT East Side Line",
         "Year": 1986
      },
      {
         "Artist": "Mickalene Thomas",
         "Title": "Untitled",
         "Station": "53rd Street",
         "Line": "BMT 4th Avenue Line",
         "Year": 2017
      },
      {
         "Artist": "Matt Mullican",
         "Title": "Untitled",
         "Station": "50th Street",
         "Line": "IND Queens Boulevard Line",
         "Year": 1989
      },
      {
         "Artist": "Scott Redden",
         "Title": "Untitled",
         "Station": "Alabama Avenue",
         "Line": "BMT Nassau Street-Jamaica Line",
         "Year": 2007
      },
      {
         "Artist": "Maku",
         "Title": "Untitled",
         "Station": "Clinton/Washington Aves.",
         "Line": "IND Crosstown Line",
         "Year": null
      },
      {
         "Artist": "Blackford/Fisher",
         "Title": "Untitled",
         "Station": "Times Square/42nd Street",
         "Line": "IRT West Side Line",
         "Year": 2003
      },
      {
         "Artist": "Frank Leslie Hampton",
         "Title": "Uptown New York",
         "Station": "Tremont Avenue",
         "Line": "IND Concourse Line",
         "Year": 2000
      },
      {
         "Artist": "Saya Woolfalk",
         "Title": "Urban Garden Rail",
         "Station": "Pennsylvania Avenue, Van Siclen Avenue",
         "Line": "IRT Brooklyn Line",
         "Year": 2017
      },
      {
         "Artist": "Elisabeth Condon",
         "Title": "Urban Idyll",
         "Station": "Ditmars Boulevard",
         "Line": "BMT Astoria Line",
         "Year": 2018
      },
      {
         "Artist": "Mario M. Muller",
         "Title": "Urban Motif",
         "Station": "Kingsbridge Road",
         "Line": "IRT Woodlawn Line",
         "Year": 2006
      },
      {
         "Artist": "Ann Schaumburger",
         "Title": "Urban Oasis",
         "Station": "5th Avenue",
         "Line": "BMT Broadway Line",
         "Year": 1997
      },
      {
         "Artist": "Christopher Sproat",
         "Title": "V-Beam",
         "Station": "Grand Central",
         "Line": "IRT Flushing Line",
         "Year": 2000
      },
      {
         "Artist": "Callie Hirsch",
         "Title": "Vast",
         "Station": "Beach 105th Street/Seaside",
         "Line": "IND Rockaway Line",
         "Year": 2011
      },
      {
         "Artist": "Dina Bursztyn",
         "Title": "Views from Above",
         "Station": "170th Street",
         "Line": "IRT Woodlawn Line",
         "Year": 2005
      },
      {
         "Artist": "Acconci/Brandt",
         "Title": "Wall-Slide/Room of Tranquility",
         "Station": "161st Street-River Avenue (Yankee Stadium), 161st Street-River Avenue (Yankee Stadium)",
         "Line": "IND Concourse Line",
         "Year": 2002
      },
      {
         "Artist": "Vito Acconci",
         "Title": "Wavewall",
         "Station": "West 8th Street",
         "Line": "BMT Brighton Line",
         "Year": 2005
      },
      {
         "Artist": "Julien Gardair",
         "Title": "We are each others",
         "Station": "Kings Highway, 18th Avenue",
         "Line": "BMT Culver Line",
         "Year": 2018
      },
      {
         "Artist": "Mary Temple",
         "Title": "West Wall, East Light, Morning",
         "Station": "Neck Road",
         "Line": "BMT Brighton Line",
         "Year": 2011
      },
      {
         "Artist": "Nitza Tufino",
         "Title": "Westside Views",
         "Station": "86th Street",
         "Line": "IRT West Side Line",
         "Year": 1989
      },
      {
         "Artist": "Lisa Amowitz",
         "Title": "What We  Build is Not Permanent, We Are Not What We Build",
         "Station": "Simpson Street",
         "Line": "IRT White Plains Road Line",
         "Year": 2006
      },
      {
         "Artist": "Jung Hyang Kim",
         "Title": "Wheel of Bloom; Soak up the Sun",
         "Station": "Crescent Street",
         "Line": "BMT Nassau Street-Jamaica Line",
         "Year": 2007
      },
      {
         "Artist": "Elizabeth Grajales",
         "Title": "When the Animals Speak",
         "Station": "34th Street/Penn Station",
         "Line": "IRT West Side Line",
         "Year": 1998
      },
      {
         "Artist": "Kambui Olujimi",
         "Title": "Where the Sky Begins",
         "Station": "Avenue I",
         "Line": "BMT Culver Line",
         "Year": 2018
      },
      {
         "Artist": "Sol Lewitt",
         "Title": "Whirls and Twirls",
         "Station": "59th Street/Columbus Circle",
         "Line": "IND 8th Avenue Line",
         "Year": 2007
      },
      {
         "Artist": "Jane Greengold",
         "Title": "Wings for the IRT, The Irresistable Romance of Travel",
         "Station": "Grand Army Plaza",
         "Line": "IRT Brooklyn Line",
         "Year": 1993
      },
      {
         "Artist": "Beatrice Lebreton",
         "Title": "Wisdom Along the Way",
         "Station": "Junius Street, Rockaway Avenue",
         "Line": "IRT Brooklyn Line",
         "Year": 2017
      },
      {
         "Artist": "Dimitri Gerakaris",
         "Title": "Woodside Continuum",
         "Station": "61st Street/Woodside",
         "Line": "IRT Flushing Line",
         "Year": 1999
      },
      {
         "Artist": "Anton van Dalen",
         "Title": "Work & Nature",
         "Station": "Nevins Street",
         "Line": "IRT Brooklyn Line",
         "Year": 1997
      },
      {
         "Artist": "David Provan",
         "Title": "Yab-Yum",
         "Station": "34th Street/Herald Square",
         "Line": "IND 6th Avenue Line",
         "Year": 1992
      },
      {
         "Artist": "Lothar Osterburg",
         "Title": "Zeppelins in Grand Central",
         "Station": "Subway Car Interior Art",
         "Line": "",
         "Year": 2013
      }
   ]